s3lify/__init__.py
s3lify/__init__.pyc
s3lify/cli.py
s3lify/cli.pyc
s3lify/s3lify.yml
s3lify-0.1.0.dist-info/METADATA
s3lify-0.1.0.dist-info/RECORD
s3lify-0.1.0.dist-info/WHEEL
s3lify-0.1.0.dist-info/entry_points.txt
s3lify-0.1.0.dist-info/top_level.txt
