Metadata-Version: 2.1
Name: s3lify
Version: 0.1.0
Summary: A script to deploy secure (SSL) single page application (SPA) or HTML static site on AWS S3, using S3, Route53, Cloudfront and ACM.
Home-page: https://github.com/mardix/s3lify
Author: Mardix
Author-email: macx2082@gmail.com
License: MIT
Platform: any
Classifier: Environment :: Web Environment
Classifier: Intended Audience :: Developers
Classifier: License :: OSI Approved :: BSD License
Classifier: Operating System :: OS Independent
Classifier: Programming Language :: Python
Classifier: Programming Language :: Python :: 2
Classifier: Programming Language :: Python :: 2.6
Classifier: Programming Language :: Python :: 2.7
Classifier: Programming Language :: Python :: 3
Classifier: Programming Language :: Python :: 3.3
Classifier: Programming Language :: Python :: 3.4
Classifier: Programming Language :: Python :: 3.5
Classifier: Topic :: Internet :: WWW/HTTP :: Dynamic Content
Classifier: Topic :: Software Development :: Libraries :: Python Modules
Requires-Dist: boto3
Requires-Dist: pyyaml
Requires-Dist: click
Requires-Dist: halo
Requires-Dist: tldextract
